<?xml version="1.0" encoding="utf-8" ?>
<Defs>

  <!--Replication-->	
	<ResearchProjectDef>
		<defName>ItemReplication</defName>
		<label>replication</label>
		<description>The foundational GTI breakthrough: persuading matter to politely copy itself. Equal parts transporter theory, voodoo, and a SCUMM script nobody on the team fully understands. Unlocks the basic principles of replication. Look behind you - a three-headed monkey!</description>
		<baseCost>5000</baseCost>
		<techLevel>Spacer</techLevel>
		<requiredResearchBuilding>HiTechResearchBench</requiredResearchBuilding>
		<requiredResearchFacilities>
			<li>MultiAnalyzer</li>
		</requiredResearchFacilities>
		<tab>RMRT</tab>
		<researchViewX>0.00</researchViewX>
		<researchViewY>0.15</researchViewY>
	</ResearchProjectDef> 
  <!--Resource Replicator-->	
	<ResearchProjectDef>
		<defName>ResourceReplicator</defName>
		<label>resource replicator</label>
		<description>Blueprints for the GTI Resource Replicator. Make it so, and never swing a pickaxe again. Steel, plasteel, components - if it built your colony, it can now build itself, twice over.</description>
		<baseCost>1500</baseCost>
		<techLevel>Spacer</techLevel>
		<prerequisites>
			<li>ItemReplication</li>
		</prerequisites>
		<requiredResearchBuilding>HiTechResearchBench</requiredResearchBuilding>
		<requiredResearchFacilities>
			<li>MultiAnalyzer</li>
		</requiredResearchFacilities>
		<tab>RMRT</tab>
		<researchViewX>1.00</researchViewX>
		<researchViewY>0.15</researchViewY>
	</ResearchProjectDef> 
  <!--Organic Replicator-->	
	<ResearchProjectDef>
		<defName>OrganicReplicator</defName>
		<label>organic replicator</label>
		<description>Blueprints for the GTI Organic Replicator. "Tea, Earl Grey, hot" - or a lavish dinner, if you've earned it. Brings food, crops and meals out of the pattern buffer, and quietly turns every mystery meat into honest beef.</description>
		<baseCost>1500</baseCost>
		<techLevel>Spacer</techLevel>
		<prerequisites>
			<li>ItemReplication</li>
		</prerequisites>
		<requiredResearchBuilding>HiTechResearchBench</requiredResearchBuilding>
		<requiredResearchFacilities>
			<li>MultiAnalyzer</li>
		</requiredResearchFacilities>
		<tab>RMRT</tab>
		<researchViewX>1.00</researchViewX>
		<researchViewY>0.60</researchViewY>
	</ResearchProjectDef>
  <!--Medicinal Replicator-->	
	<ResearchProjectDef>
		<defName>MedicinalReplicator</defName>
		<label>medicinal replicator</label>
		<description>Blueprints for the GTI Medicinal Replicator. Healing, pharmaceuticals, and a suspicious quantity of root beer, all conjured from a stored pattern. The GTI motto applies: "It probably won't kill you, and look behind you!"</description>
		<baseCost>1500</baseCost>
		<techLevel>Spacer</techLevel>
		<prerequisites>
			<li>ItemReplication</li>
		</prerequisites>
		<requiredResearchBuilding>HiTechResearchBench</requiredResearchBuilding>
		<requiredResearchFacilities>
			<li>MultiAnalyzer</li>
		</requiredResearchFacilities>
		<tab>RMRT</tab>
		<researchViewX>1.00</researchViewX>
		<researchViewY>1.05</researchViewY>
	</ResearchProjectDef> 			

</Defs>